.flake8
.pre-commit-config.yaml
.readthedocs.yaml
CHANGELOG.rst
CONTRIBUTING.rst
LICENSE
MANIFEST.in
Makefile
README.rst
ansible.cfg
dev-requirements.txt
mypy.ini
pyproject.toml
setup.cfg
setup.py
test-requirements.txt
tox.ini
doc/Makefile
doc/source/api.rst
doc/source/backends.rst
doc/source/changelog.rst
doc/source/conf.py
doc/source/examples.rst
doc/source/index.rst
doc/source/invocation.rst
doc/source/modules.rst
doc/source/support.rst
doc/source/_static/logo.svg
doc/source/_templates/piwik.html
images/debian_bookworm/Dockerfile
images/rockylinux9/Dockerfile
pytest_testinfra_jpic.egg-info/PKG-INFO
pytest_testinfra_jpic.egg-info/SOURCES.txt
pytest_testinfra_jpic.egg-info/dependency_links.txt
pytest_testinfra_jpic.egg-info/entry_points.txt
pytest_testinfra_jpic.egg-info/requires.txt
pytest_testinfra_jpic.egg-info/top_level.txt
test/conftest.py
test/ssh_key
test/test_backends.py
test/test_invocation.py
test/test_modules.py
testinfra/__init__.py
testinfra/host.py
testinfra/main.py
testinfra/plugin.py
testinfra/backend/__init__.py
testinfra/backend/ansible.py
testinfra/backend/base.py
testinfra/backend/chroot.py
testinfra/backend/docker.py
testinfra/backend/kubectl.py
testinfra/backend/local.py
testinfra/backend/lxc.py
testinfra/backend/openshift.py
testinfra/backend/paramiko.py
testinfra/backend/podman.py
testinfra/backend/salt.py
testinfra/backend/ssh.py
testinfra/backend/winrm.py
testinfra/modules/__init__.py
testinfra/modules/addr.py
testinfra/modules/ansible.py
testinfra/modules/base.py
testinfra/modules/blockdevice.py
testinfra/modules/command.py
testinfra/modules/docker.py
testinfra/modules/environment.py
testinfra/modules/file.py
testinfra/modules/group.py
testinfra/modules/interface.py
testinfra/modules/iptables.py
testinfra/modules/mountpoint.py
testinfra/modules/package.py
testinfra/modules/pip.py
testinfra/modules/podman.py
testinfra/modules/process.py
testinfra/modules/puppet.py
testinfra/modules/salt.py
testinfra/modules/service.py
testinfra/modules/socket.py
testinfra/modules/sudo.py
testinfra/modules/supervisor.py
testinfra/modules/sysctl.py
testinfra/modules/systeminfo.py
testinfra/modules/user.py
testinfra/utils/__init__.py
testinfra/utils/ansible_runner.py